pyexpert/__init__.py
pyexpert/narrate.py
pyexpert/prolog.py
pyexpert/prolog_ast.py
pyexpert/prolog_parser.py
pyexpert-0.0.1.dist-info/DESCRIPTION.rst
pyexpert-0.0.1.dist-info/METADATA
pyexpert-0.0.1.dist-info/RECORD
pyexpert-0.0.1.dist-info/WHEEL
pyexpert-0.0.1.dist-info/metadata.json
pyexpert-0.0.1.dist-info/top_level.txt
