Metadata-Version: 2.0
Name: pyexpert
Version: 0.0.1
Summary: A small prolog implementation for embedded expert systems
Home-page: UNKNOWN
Author: UNKNOWN
Author-email: UNKNOWN
License: MIT
Keywords: prolog
Platform: UNKNOWN
Requires-Dist: arpeggio
